Workbook

Sheet table
A1: Order ID | B1: Date | C1: Product | D1: Price | E1: Quantity Updated | F1: Quantity | G1: Cost | H1: Purchase Type | I1: Payment Method | J1: Manager Updated | K1: Manager | L1: City | M1: Country | N1: Profitability | O1: Revenue
A2: 20904 | B2: 45237 | C2: Personal Care Products | D2: 8.725 | E2: 58 | F2: 57.30659 | G2: 4.4 | H2: Online | I2: Gift Card | J2: John Johnson | K2: John Johnson | L2: London | M2: =IF(L2="London","UK", IF(L2="Madrid","Spain", IF(L2="Paris","France", IF(L2="Berlin","Germany", IF(L2="Lisbon","Portugal",""))))) -> UK | N2: =(D2-G2)*E2 -> 250.85 | O2: =D2*E2 -> 506.05
A3: 20906 | B3: 45237 | C3: Beverages | D3: 7.375 | E3: 75 | F3: 74.576271 | G3: 2.35 | H3: Online | I3: Gift Card | J3: Hugo Lopez | K3: Hugo Lopez | L3: Madrid | M3: =IF(L3="London","UK", IF(L3="Madrid","Spain", IF(L3="Paris","France", IF(L3="Berlin","Germany", IF(L3="Lisbon","Portugal",""))))) -> Spain | N3: =(D3-G3)*E3 -> 376.875 | O3: =D3*E3 -> 553.125
A4: 20908 | B4: 45237 | C4: Convenience Items | D4: 12.475 | E4: 21 | F4: 20.04008 | G4: 11.25 | H4: In-store | I4: Gift Card | J4: Afonso Santos | K4: Afonso Santos | L4: Lisbon | M4: =IF(L4="London","UK", IF(L4="Madrid","Spain", IF(L4="Paris","France", IF(L4="Berlin","Germany", IF(L4="Lisbon","Portugal",""))))) -> Portugal | N4: =(D4-G4)*E4 -> 25.725 | O4: =D4*E4 -> 261.975
A5: 20910 | B5: 45238 | C5: Groceries | D5: 32.475 | E5: 57 | F5: 56.966898 | G5: 21.6 | H5: In-store | I5: Credit Card | J5: Hans Wagner | K5: Hans Wagner | L5: Berlin | M5: =IF(L5="London","UK", IF(L5="Madrid","Spain", IF(L5="Paris","France", IF(L5="Berlin","Germany", IF(L5="Lisbon","Portugal",""))))) -> Germany | N5: =(D5-G5)*E5 -> 619.875 | O5: =D5*E5 -> 1851.075
A6: 20912 | B6: 45238 | C6: Household Items | D6: 24.875 | E6: 21 | F6: 20.100503 | G6: 14.25 | H6: In-store | I6: Credit Card | J6: Hans Wagner | K6: Hans Wagner | L6: Berlin | M6: =IF(L6="London","UK", IF(L6="Madrid","Spain", IF(L6="Paris","France", IF(L6="Berlin","Germany", IF(L6="Lisbon","Portugal",""))))) -> Germany | N6: =(D6-G6)*E6 -> 223.125 | O6: =D6*E6 -> 522.375
A7: 20914 | B7: 45238 | C7: Personal Care Products | D7: 8.725 | E7: 58 | F7: 57.30659 | G7: 4.4 | H7: In-store | I7: Credit Card | J7: Marc Laurent | K7: Marc Laurent | L7: Paris | M7: =IF(L7="London","UK", IF(L7="Madrid","Spain", IF(L7="Paris","France", IF(L7="Berlin","Germany", IF(L7="Lisbon","Portugal",""))))) -> France | N7: =(D7-G7)*E7 -> 250.85 | O7: =D7*E7 -> 506.05
A8: 20918 | B8: 45238 | C8: Convenience Items | D8: 12.475 | E8: 21 | F8: 20.04008 | G8: 11.25 | H8: In-store | I8: Credit Card | J8: Hans Wagner | K8: Hans Wagner | L8: Berlin | M8: =IF(L8="London","UK", IF(L8="Madrid","Spain", IF(L8="Paris","France", IF(L8="Berlin","Germany", IF(L8="Lisbon","Portugal",""))))) -> Germany | N8: =(D8-G8)*E8 -> 25.725 | O8: =D8*E8 -> 261.975
A9: 20950 | B9: 45242 | C9: Groceries | D9: 32.475 | E9: 53 | F9: 52.34796 | G9: 21.6 | H9: In-store | I9: Credit Card | J9: Hugo Lopez | K9: Hugo Lopez | L9: Madrid | M9: =IF(L9="London","UK", IF(L9="Madrid","Spain", IF(L9="Paris","France", IF(L9="Berlin","Germany", IF(L9="Lisbon","Portugal",""))))) -> Spain | N9: =(D9-G9)*E9 -> 576.375 | O9: =D9*E9 -> 1721.175
A10: 20952 | B10: 45242 | C10: Household Items | D10: 24.875 | E10: 21 | F10: 20.100503 | G10: 14.25 | H10: In-store | I10: Credit Card | J10: Hugo Lopez | K10: Hugo Lopez | L10: Madrid | M10: =IF(L10="London","UK", IF(L10="Madrid","Spain", IF(L10="Paris","France", IF(L10="Berlin","Germany", IF(L10="Lisbon","Portugal",""))))) -> Spain | N10: =(D10-G10)*E10 -> 223.125 | O10: =D10*E10 -> 522.375
A11: 20954 | B11: 45242 | C11: Personal Care Products | D11: 8.725 | E11: 64 | F11: 63.037249 | G11: 4.4 | H11: In-store | I11: Credit Card | J11: Hugo Lopez | K11: Hugo Lopez | L11: Madrid | M11: =IF(L11="London","UK", IF(L11="Madrid","Spain", IF(L11="Paris","France", IF(L11="Berlin","Germany", IF(L11="Lisbon","Portugal",""))))) -> Spain | N11: =(D11-G11)*E11 -> 276.8 | O11: =D11*E11 -> 558.4
A12: 20956 | B12: 45242 | C12: Beverages | D12: 7.375 | E12: 68 | F12: 67.79661 | G12: 2.35 | H12: In-store | I12: Credit Card | J12: Hugo Lopez | K12: Hugo Lopez | L12: Madrid | M12: =IF(L12="London","UK", IF(L12="Madrid","Spain", IF(L12="Paris","France", IF(L12="Berlin","Germany", IF(L12="Lisbon","Portugal",""))))) -> Spain | N12: =(D12-G12)*E12 -> 341.7 | O12: =D12*E12 -> 501.5
A13: 20958 | B13: 45242 | C13: Convenience Items | D13: 12.475 | E13: 21 | F13: 20.04008 | G13: 11.25 | H13: In-store | I13: Credit Card | J13: Hugo Lopez | K13: Hugo Lopez | L13: Madrid | M13: =IF(L13="London","UK", IF(L13="Madrid","Spain", IF(L13="Paris","France", IF(L13="Berlin","Germany", IF(L13="Lisbon","Portugal",""))))) -> Spain | N13: =(D13-G13)*E13 -> 25.725 | O13: =D13*E13 -> 261.975
... A244: 21426 | B244: 45289 | C244: Beverages | D244: 7.375 | E244: 68 | F244: 67.79661 | G244: 2.35 | H244: Drive-thru | I244: Gift Card | J244: Hans Wagner | K244: Hans Wagner | L244: Berlin | M244: =IF(L244="London","UK", IF(L244="Madrid","Spain", IF(L244="Paris","France", IF(L244="Berlin","Germany", IF(L244="Lisbon","Portugal",""))))) -> Germany | N244: =(D244-G244)*E244 -> 341.7 | O244: =D244*E244 -> 501.5

Sheet DESCRIPTIVE STATISTICS
L7: Boxplot And Whisker
D11: Metrics | E11: Price | F11: Quantity
D12: Mean | E12: 18.400412 | F12: 46.057567
D13: Standard Error | E13: 0.78845625 | F13: 1.3826492
D14: Median | E14: 12.475 | F14: 53.887606
D15: Mode | E15: 32.475 | F15: 20.04008
D16: Standard Deviation | E16: 12.290817 | F16: 21.553369
D17: Sample Variance | E17: 151.06417 | F17: 464.5477
D18: Kurtosis | E18: 4.781899 | F18: -1.7303409
D19: Skewness | E19: 1.6561328 | F19: -0.20262529
D20: Range | E20: 75.675 | F20: 55.402568
D21: Minimum | E21: 7.375 | F21: 20.04008
D22: Maximum | E22: 83.05 | F22: 75.442648
D23: Sum | E23: 4471.3 | F23: 11191.989
D24: Count | E24: 243 | F24: 243
J25: Afonso Santos shows most outliers

Sheet Data Analysis
A3: Total Revenue | B3: Total Profitability | D3: Most Profitability Product
A4: 195246.45 | B4: 75957.3 | D4: Row Labels | E4: Sum of Profitability
D5: Groceries | E5: 47887.575 | H5: Payment Distribution
D6: Household Items | E6: 16348.075 | G6: Sum of Revenue | H6: Column Labels
D7: Personal Care Products | E7: 8151.175 | G7: Row Labels | H7: Cash | I7: Credit Card | J7: Gift Card | K7: Grand Total
D8: Beverages | E8: 2707.9 | G8: Drive-thru | H8: 0.068487929 | I8: 0.11797334 | J8: 0.045967673 | K8: 0.23242894
D9: Convenience Items | E9: 862.575 | G9: In-store | H9: 0.18805015 | I9: 0.17880786 | J9: 0.0039103144 | K9: 0.37076833
D10: Grand Total | E10: 75957.3 | G10: Online | H10: 0.054124159 | I10: 0.17347166 | J10: 0.16920692 | K10: 0.39680273
G11: Grand Total | H11: 0.31066224 | I11: 0.47025285 | J11: 0.21908491 | K11: 1
D15: Row Labels | E15: Sum of Revenue
D16: Nov | E16: 84286.25
D17: Dec | E17: 110960.2
D18: Grand Total | E18: 195246.45

Sheet report
A2: Manager | B2: Afonso Santos | G2: Sales Trend
A3: City | B3: =_xlfn.XLOOKUP(B2,table!J2:J244,table!L2:L244) -> Lisbon
A4: Country | B4: =_xlfn.XLOOKUP(B2,table!J2:J244,table!M2:M244) -> Portugal
A5: Total Sales | B5: =SUMIFS(table!N2:N244,table!J2:J244,report!B2) -> 35553.1
A6: Product | B6: Revenue
A7: Convenience Items | B7: =SUMIFS(table!N2:N244,table!J2:J244,report!B2,table!C2:C244,report!A8) -> 5146.925
A8: Household Items | B8: =SUMIFS( table!N2:N244,table!J2:J244,report!B2,table!C2:C244,report!A8) -> 5146.925
A9: Beverages | B9: =SUMIFS(table!N3:N245,table!J3:J245,report!B2,table!C3:C245,A9) -> 9787.8
A10: Personal Care Products | B10: =SUMIFS(table!N4:N246,table!J4:J246,report!B2,table!C4:C246,report!A10) -> 6186.65
A11: Groceries | B11: =SUMIFS(table!N5:N247,table!J5:J247,report!B2,table!C5:C247,report!A11) -> 13654.2
